speechgpt/__init__.py
speechgpt/askgpt.py
speechgpt/text_to_speech.py
speechgpt/voiceinterface.py
speechgpt-0.1.3.dist-info/LICENSE
speechgpt-0.1.3.dist-info/METADATA
speechgpt-0.1.3.dist-info/WHEEL
speechgpt-0.1.3.dist-info/top_level.txt
speechgpt-0.1.3.dist-info/RECORD
