Metadata-Version: 2.1
Name: speechgpt
Version: 0.1.3
Summary: A voice interface for OpenAI's ChatGPT
Author-email: Jdka1 <arymehr@nuevaschool.org>
Project-URL: Homepage, https://github.com/Jdka1/SpeechGPT
Project-URL: Bug Tracker, https://github.com/Jdka1/SpeechGPT/issues
Classifier: Programming Language :: Python :: 3
Classifier: License :: OSI Approved :: MIT License
Classifier: Operating System :: OS Independent
Requires-Python: >=3.7
License-File: LICENSE
Requires-Dist: pyChatGPT
Requires-Dist: pyttsx3
Requires-Dist: SpeechRecognition
